{"1": {"libname": "oppia", "filename": "oppia-player.min.js", "url": "https://cdnjs.cloudflare.com/ajax/libs/oppia/0.0.1/oppia-player.min.js", "version": "0.0.1", "in_deps": [], "out_deps": [], "success": true}, "2": {"libname": "oppia", "filename": "oppia-player.min.js", "url": "https://cdnjs.cloudflare.com/ajax/libs/oppia/0.0.2/oppia-player.min.js", "version": "0.0.2", "in_deps": [], "out_deps": [], "success": true}, "3": {"libname": "oppia", "filename": "oppia-player.js", "url": "https://cdnjs.cloudflare.com/ajax/libs/oppia/0.0.3/oppia-player.js", "version": "0.0.3", "in_deps": [], "out_deps": [], "success": true}}