{"1": {"libname": "snabbdom", "filename": "snabbdom.js", "url": "https://cdnjs.cloudflare.com/ajax/libs/snabbdom/0.5.1/snabbdom.js", "version": "0.5.1", "in_deps": [], "out_deps": [], "success": true}, "2": {"libname": "snabbdom", "filename": "snabbdom.js", "url": "https://cdnjs.cloudflare.com/ajax/libs/snabbdom/0.5.2/snabbdom.js", "version": "0.5.2", "in_deps": [], "out_deps": [], "success": true}, "3": {"libname": "snabbdom", "filename": "snabbdom.js", "url": "https://cdnjs.cloudflare.com/ajax/libs/snabbdom/0.5.3/snabbdom.js", "version": "0.5.3", "in_deps": [], "out_deps": [], "success": true}, "4": {"libname": "snabbdom", "filename": "snabbdom.js", "url": "https://cdnjs.cloudflare.com/ajax/libs/snabbdom/0.5.4/snabbdom.js", "version": "0.5.4", "in_deps": [], "out_deps": [], "success": true}, "5": {"libname": "snabbdom", "filename": "snabbdom.js", "url": "https://cdnjs.cloudflare.com/ajax/libs/snabbdom/0.6.0/snabbdom.js", "version": "0.6.0", "in_deps": [], "out_deps": [], "success": true}, "6": {"libname": "snabbdom", "filename": "snabbdom.js", "url": "https://cdnjs.cloudflare.com/ajax/libs/snabbdom/0.6.1/snabbdom.js", "version": "0.6.1", "in_deps": [], "out_deps": [], "success": true}, "7": {"libname": "snabbdom", "filename": "snabbdom.js", "url": "https://cdnjs.cloudflare.com/ajax/libs/snabbdom/0.6.2/snabbdom.js", "version": "0.6.2", "in_deps": [], "out_deps": [], "success": true}, "8": {"libname": "snabbdom", "filename": "snabbdom.js", "url": "https://cdnjs.cloudflare.com/ajax/libs/snabbdom/0.6.3/snabbdom.js", "version": "0.6.3", "in_deps": [], "out_deps": [], "success": true}, "9": {"libname": "snabbdom", "filename": "snabbdom.js", "url": "https://cdnjs.cloudflare.com/ajax/libs/snabbdom/0.6.4/snabbdom.js", "version": "0.6.4", "in_deps": [], "out_deps": [], "success": true}, "10": {"libname": "snabbdom", "filename": "snabbdom.js", "url": "https://cdnjs.cloudflare.com/ajax/libs/snabbdom/0.6.5/snabbdom.js", "version": "0.6.5", "in_deps": [], "out_deps": [], "success": true}, "11": {"libname": "snabbdom", "filename": "snabbdom.js", "url": "https://cdnjs.cloudflare.com/ajax/libs/snabbdom/0.6.6/snabbdom.js", "version": "0.6.6", "in_deps": [], "out_deps": [], "success": true}, "12": {"libname": "snabbdom", "filename": "snabbdom.js", "url": "https://cdnjs.cloudflare.com/ajax/libs/snabbdom/0.6.7/snabbdom.js", "version": "0.6.7", "in_deps": [], "out_deps": [], "success": true}, "13": {"libname": "snabbdom", "filename": "snabbdom.js", "url": "https://cdnjs.cloudflare.com/ajax/libs/snabbdom/0.6.8/snabbdom.js", "version": "0.6.8", "in_deps": [], "out_deps": [], "success": true}, "14": {"libname": "snabbdom", "filename": "snabbdom.js", "url": "https://cdnjs.cloudflare.com/ajax/libs/snabbdom/0.6.9/snabbdom.js", "version": "0.6.9", "in_deps": [], "out_deps": [], "success": true}, "15": {"libname": "snabbdom", "filename": "snabbdom.js", "url": "https://cdnjs.cloudflare.com/ajax/libs/snabbdom/0.7.0/snabbdom.js", "version": "0.7.0", "in_deps": [], "out_deps": [], "success": true}, "16": {"libname": "snabbdom", "filename": "snabbdom.js", "url": "https://cdnjs.cloudflare.com/ajax/libs/snabbdom/0.7.1/snabbdom.js", "version": "0.7.1", "in_deps": [], "out_deps": [], "success": true}, "17": {"libname": "snabbdom", "filename": "snabbdom.js", "url": "https://cdnjs.cloudflare.com/ajax/libs/snabbdom/0.7.2/snabbdom.js", "version": "0.7.2", "in_deps": [], "out_deps": [], "success": true}, "18": {"libname": "snabbdom", "filename": "snabbdom.js", "url": "https://cdnjs.cloudflare.com/ajax/libs/snabbdom/0.7.3/snabbdom.js", "version": "0.7.3", "in_deps": [], "out_deps": [], "success": true}, "19": {"libname": "snabbdom", "filename": "snabbdom.js", "url": "https://cdnjs.cloudflare.com/ajax/libs/snabbdom/0.7.4/snabbdom.js", "version": "0.7.4", "in_deps": [], "out_deps": [], "success": true}, "20": {"libname": "snabbdom", "filename": "", "url": "", "version": "1.0.1", "in_deps": [], "out_deps": [], "success": true}, "21": {"libname": "snabbdom", "filename": "", "url": "", "version": "2.0.0", "in_deps": [], "out_deps": [], "success": true}, "22": {"libname": "snabbdom", "filename": "", "url": "", "version": "2.1.0", "in_deps": [], "out_deps": [], "success": true}, "23": {"libname": "snabbdom", "filename": "", "url": "", "version": "3.0.0", "in_deps": [], "out_deps": [], "success": true}, "24": {"libname": "snabbdom", "filename": "", "url": "", "version": "3.0.1", "in_deps": [], "out_deps": [], "success": true}, "25": {"libname": "snabbdom", "filename": "", "url": "", "version": "3.0.2", "in_deps": [], "out_deps": [], "success": true}, "26": {"libname": "snabbdom", "filename": "", "url": "", "version": "3.0.3", "in_deps": [], "out_deps": [], "success": true}, "27": {"libname": "snabbdom", "filename": "", "url": "", "version": "3.1.0", "in_deps": [], "out_deps": [], "success": true}, "28": {"libname": "snabbdom", "filename": "", "url": "", "version": "3.2.0", "in_deps": [], "out_deps": [], "success": true}, "29": {"libname": "snabbdom", "filename": "", "url": "", "version": "3.3.0", "in_deps": [], "out_deps": [], "success": true}, "30": {"libname": "snabbdom", "filename": "", "url": "", "version": "3.3.1", "in_deps": [], "out_deps": [], "success": true}, "31": {"libname": "snabbdom", "filename": "", "url": "", "version": "3.4.0", "in_deps": [], "out_deps": [], "success": true}, "32": {"libname": "snabbdom", "filename": "", "url": "", "version": "3.5.0", "in_deps": [], "out_deps": [], "success": true}, "33": {"libname": "snabbdom", "filename": "", "url": "", "version": "3.5.1", "in_deps": [], "out_deps": [], "success": true}, "34": {"libname": "snabbdom", "filename": "", "url": "", "version": "3.6.0", "in_deps": [], "out_deps": [], "success": true}, "35": {"libname": "snabbdom", "filename": "", "url": "", "version": "3.6.1", "in_deps": [], "out_deps": [], "success": true}, "36": {"libname": "snabbdom", "filename": "", "url": "", "version": "3.6.2", "in_deps": [], "out_deps": [], "success": true}}