{"1": {"libname": "tachyons", "filename": "", "url": "", "version": ".4.5.0", "in_deps": [], "out_deps": [], "success": true}, "2": {"libname": "tachyons", "filename": "", "url": "", "version": "1.1.0", "in_deps": [], "out_deps": [], "success": true}, "3": {"libname": "tachyons", "filename": "", "url": "", "version": "1.1.1", "in_deps": [], "out_deps": [], "success": true}, "4": {"libname": "tachyons", "filename": "", "url": "", "version": "1.2.0", "in_deps": [], "out_deps": [], "success": true}, "5": {"libname": "tachyons", "filename": "", "url": "", "version": "1.3.0", "in_deps": [], "out_deps": [], "success": true}, "6": {"libname": "tachyons", "filename": "", "url": "", "version": "1.3.1", "in_deps": [], "out_deps": [], "success": true}, "7": {"libname": "tachyons", "filename": "", "url": "", "version": "1.4.0", "in_deps": [], "out_deps": [], "success": true}, "8": {"libname": "tachyons", "filename": "", "url": "", "version": "2.0.0", "in_deps": [], "out_deps": [], "success": true}, "9": {"libname": "tachyons", "filename": "", "url": "", "version": "2.0.1", "in_deps": [], "out_deps": [], "success": true}, "10": {"libname": "tachyons", "filename": "", "url": "", "version": "2.1.0", "in_deps": [], "out_deps": [], "success": true}, "11": {"libname": "tachyons", "filename": "", "url": "", "version": "2.1.1", "in_deps": [], "out_deps": [], "success": true}, "12": {"libname": "tachyons", "filename": "", "url": "", "version": "3.0.0", "in_deps": [], "out_deps": [], "success": true}, "13": {"libname": "tachyons", "filename": "", "url": "", "version": "3.0.1", "in_deps": [], "out_deps": [], "success": true}, "14": {"libname": "tachyons", "filename": "", "url": "", "version": "3.0.2", "in_deps": [], "out_deps": [], "success": true}, "15": {"libname": "tachyons", "filename": "", "url": "", "version": "4.0.0-beta.10", "in_deps": [], "out_deps": [], "success": true}, "16": {"libname": "tachyons", "filename": "", "url": "", "version": "4.0.0-beta.15", "in_deps": [], "out_deps": [], "success": true}, "17": {"libname": "tachyons", "filename": "", "url": "", "version": "4.0.0-beta.16", "in_deps": [], "out_deps": [], "success": true}, "18": {"libname": "tachyons", "filename": "", "url": "", "version": "4.0.0-beta.17", "in_deps": [], "out_deps": [], "success": true}, "19": {"libname": "tachyons", "filename": "", "url": "", "version": "4.0.0-beta.18", "in_deps": [], "out_deps": [], "success": true}, "20": {"libname": "tachyons", "filename": "", "url": "", "version": "4.0.0-beta.20", "in_deps": [], "out_deps": [], "success": true}, "21": {"libname": "tachyons", "filename": "", "url": "", "version": "4.0.0-beta.25", "in_deps": [], "out_deps": [], "success": true}, "22": {"libname": "tachyons", "filename": "", "url": "", "version": "4.0.0-beta.26", "in_deps": [], "out_deps": [], "success": true}, "23": {"libname": "tachyons", "filename": "", "url": "", "version": "4.0.0-beta.3", "in_deps": [], "out_deps": [], "success": true}, "24": {"libname": "tachyons", "filename": "", "url": "", "version": "4.0.0-beta.32", "in_deps": [], "out_deps": [], "success": true}, "25": {"libname": "tachyons", "filename": "", "url": "", "version": "4.0.0-beta.34", "in_deps": [], "out_deps": [], "success": true}, "26": {"libname": "tachyons", "filename": "", "url": "", "version": "4.0.0-beta.35", "in_deps": [], "out_deps": [], "success": true}, "27": {"libname": "tachyons", "filename": "", "url": "", "version": "4.0.0-beta.9", "in_deps": [], "out_deps": [], "success": true}, "28": {"libname": "tachyons", "filename": "", "url": "", "version": "4.0.0-beta1", "in_deps": [], "out_deps": [], "success": true}, "29": {"libname": "tachyons", "filename": "", "url": "", "version": "4.0.1", "in_deps": [], "out_deps": [], "success": true}, "30": {"libname": "tachyons", "filename": "", "url": "", "version": "4.0.1-beta", "in_deps": [], "out_deps": [], "success": true}, "31": {"libname": "tachyons", "filename": "", "url": "", "version": "4.0.2", "in_deps": [], "out_deps": [], "success": true}, "32": {"libname": "tachyons", "filename": "", "url": "", "version": "4.0.3", "in_deps": [], "out_deps": [], "success": true}, "33": {"libname": "tachyons", "filename": "", "url": "", "version": "4.0.4", "in_deps": [], "out_deps": [], "success": true}, "34": {"libname": "tachyons", "filename": "", "url": "", "version": "4.0.5", "in_deps": [], "out_deps": [], "success": true}, "35": {"libname": "tachyons", "filename": "", "url": "", "version": "4.0.6", "in_deps": [], "out_deps": [], "success": true}, "36": {"libname": "tachyons", "filename": "", "url": "", "version": "4.0.7", "in_deps": [], "out_deps": [], "success": true}, "37": {"libname": "tachyons", "filename": "", "url": "", "version": "4.0.8", "in_deps": [], "out_deps": [], "success": true}, "38": {"libname": "tachyons", "filename": "", "url": "", "version": "4.1.0", "in_deps": [], "out_deps": [], "success": true}, "39": {"libname": "tachyons", "filename": "", "url": "", "version": "4.1.1", "in_deps": [], "out_deps": [], "success": true}, "40": {"libname": "tachyons", "filename": "", "url": "", "version": "4.1.2", "in_deps": [], "out_deps": [], "success": true}, "41": {"libname": "tachyons", "filename": "", "url": "", "version": "4.1.3", "in_deps": [], "out_deps": [], "success": true}, "42": {"libname": "tachyons", "filename": "", "url": "", "version": "4.11.0", "in_deps": [], "out_deps": [], "success": true}, "43": {"libname": "tachyons", "filename": "", "url": "", "version": "4.11.1", "in_deps": [], "out_deps": [], "success": true}, "44": {"libname": "tachyons", "filename": "", "url": "", "version": "4.2.0", "in_deps": [], "out_deps": [], "success": true}, "45": {"libname": "tachyons", "filename": "", "url": "", "version": "4.2.1", "in_deps": [], "out_deps": [], "success": true}, "46": {"libname": "tachyons", "filename": "", "url": "", "version": "4.3.0", "in_deps": [], "out_deps": [], "success": true}, "47": {"libname": "tachyons", "filename": "", "url": "", "version": "4.4.1", "in_deps": [], "out_deps": [], "success": true}, "48": {"libname": "tachyons", "filename": "", "url": "", "version": "4.5.0", "in_deps": [], "out_deps": [], "success": true}, "49": {"libname": "tachyons", "filename": "", "url": "", "version": "4.5.2", "in_deps": [], "out_deps": [], "success": true}, "50": {"libname": "tachyons", "filename": "", "url": "", "version": "4.5.4", "in_deps": [], "out_deps": [], "success": true}, "51": {"libname": "tachyons", "filename": "", "url": "", "version": "4.5.5", "in_deps": [], "out_deps": [], "success": true}, "52": {"libname": "tachyons", "filename": "", "url": "", "version": "4.6.0", "in_deps": [], "out_deps": [], "success": true}, "53": {"libname": "tachyons", "filename": "", "url": "", "version": "4.6.1", "in_deps": [], "out_deps": [], "success": true}, "54": {"libname": "tachyons", "filename": "", "url": "", "version": "4.6.2", "in_deps": [], "out_deps": [], "success": true}, "55": {"libname": "tachyons", "filename": "", "url": "", "version": "4.7.0", "in_deps": [], "out_deps": [], "success": true}, "56": {"libname": "tachyons", "filename": "", "url": "", "version": "4.7.1", "in_deps": [], "out_deps": [], "success": true}, "57": {"libname": "tachyons", "filename": "", "url": "", "version": "4.7.2", "in_deps": [], "out_deps": [], "success": true}, "58": {"libname": "tachyons", "filename": "", "url": "", "version": "4.7.3", "in_deps": [], "out_deps": [], "success": true}, "59": {"libname": "tachyons", "filename": "", "url": "", "version": "4.7.4", "in_deps": [], "out_deps": [], "success": true}, "60": {"libname": "tachyons", "filename": "", "url": "", "version": "4.8.0", "in_deps": [], "out_deps": [], "success": true}, "61": {"libname": "tachyons", "filename": "", "url": "", "version": "4.8.1", "in_deps": [], "out_deps": [], "success": true}, "62": {"libname": "tachyons", "filename": "", "url": "", "version": "4.9.0", "in_deps": [], "out_deps": [], "success": true}, "63": {"libname": "tachyons", "filename": "", "url": "", "version": "4.9.1", "in_deps": [], "out_deps": [], "success": true}, "64": {"libname": "tachyons", "filename": "", "url": "", "version": "7.0.1-0", "in_deps": [], "out_deps": [], "success": true}, "65": {"libname": "tachyons", "filename": "", "url": "", "version": "7.0.1-1", "in_deps": [], "out_deps": [], "success": true}, "66": {"libname": "tachyons", "filename": "", "url": "", "version": "7.0.1-3", "in_deps": [], "out_deps": [], "success": true}, "67": {"libname": "tachyons", "filename": "", "url": "", "version": "7.0.1-4", "in_deps": [], "out_deps": [], "success": true}}