[{"version": "3.2.0", "files": ["images/icons-000000@2x.png", "images/icons-ffffff.svg", "images/icons-ffffff@2x.png", "images/icons.svg", "images/layers-2x.png", "images/layers.png", "images/marker-icon-2x.png", "images/marker-icon.png", "images/marker-shadow.png", "mapbox.css", "mapbox.internals.js", "mapbox.js", "mapbox.js.map", "mapbox.min.css", "mapbox.standalone.css", "mapbox.standalone.js", "mapbox.standalone.js.map", "mapbox.standalone.min.css", "mapbox.standalone.uncompressed.js", "mapbox.uncompressed.css", "mapbox.uncompressed.js", "mapbox.uncompressed.min.css"]}, {"version": "3.2.1", "files": ["images/icons-000000@2x.png", "images/icons-ffffff.svg", "images/icons-ffffff@2x.png", "images/icons.svg", "images/layers-2x.png", "images/layers.png", "images/marker-icon-2x.png", "images/marker-icon.png", "images/marker-shadow.png", "mapbox.css", "mapbox.internals.js", "mapbox.js", "mapbox.js.map", "mapbox.min.css", "mapbox.standalone.css", "mapbox.standalone.js", "mapbox.standalone.js.map", "mapbox.standalone.min.css", "mapbox.standalone.uncompressed.js", "mapbox.uncompressed.css", "mapbox.uncompressed.js", "mapbox.uncompressed.min.css"]}, {"version": "3.3.0", "files": ["images/icons-000000@2x.png", "images/icons-ffffff.svg", "images/icons-ffffff@2x.png", "images/icons.svg", "images/layers-2x.png", "images/layers.png", "images/marker-icon-2x.png", "images/marker-icon.png", "images/marker-shadow.png", "mapbox.css", "mapbox.internals.js", "mapbox.js", "mapbox.js.map", "mapbox.min.css", "mapbox.standalone.css", "mapbox.standalone.js", "mapbox.standalone.js.map", "mapbox.standalone.min.css", "mapbox.standalone.uncompressed.js", "mapbox.uncompressed.css", "mapbox.uncompressed.js", "mapbox.uncompressed.min.css"]}, {"version": "3.3.1", "files": ["images/icons-000000@2x.png", "images/icons-ffffff.svg", "images/icons-ffffff@2x.png", "images/icons.svg", "images/images/icons-000000@2x.png", "images/images/icons-ffffff.svg", "images/images/icons-ffffff@2x.png", "images/images/icons.svg", "images/images/layers-2x.png", "images/images/layers.png", "images/images/marker-icon-2x.png", "images/images/marker-icon.png", "images/images/marker-shadow.png", "images/layers-2x.png", "images/layers.png", "images/marker-icon-2x.png", "images/marker-icon.png", "images/marker-shadow.png", "mapbox.css", "mapbox.internals.js", "mapbox.js", "mapbox.js.map", "mapbox.min.css", "mapbox.standalone.css", "mapbox.standalone.js", "mapbox.standalone.js.map", "mapbox.standalone.min.css", "mapbox.standalone.uncompressed.js", "mapbox.uncompressed.css", "mapbox.uncompressed.js", "mapbox.uncompressed.min.css"]}]